README.md
setup.cfg
setup.py
qbackup/__init__.py
qbackup/config.py
qbackup/source.py
qbackup/target.py
qbackup.egg-info/PKG-INFO
qbackup.egg-info/SOURCES.txt
qbackup.egg-info/dependency_links.txt
qbackup.egg-info/top_level.txt
qbackup/filters/__init__.py
qbackup/sources/__init__.py
qbackup/sources/dir.py
qbackup/sources/file.py
qbackup/targets/__init__.py
qbackup/targets/disk.py
qbackup/targets/ftp.py
qbackup/targets/google_drive.py
qbackup/targets/ipfs.py
qbackup/targets/microsoft_onedrive.py
qbackup/targets/s3.py
qbackup/targets/samba.py
qbackup/tasks/__init__.py
qbackup/tasks/local_file_copy/__init__.py
qbackup/tasks/local_file_copy/filecopy.py
qbackup/tasks/local_file_copy/test_filecopy.py