Metadata-Version: 2.1
Name: qbackup
Version: 0.0.1
Summary: Cross-Platform multi-purpose backup utility
Home-page: https://github.com/randydu/qbackup.git
Author: randydu
Author-email: randydu@gmail.com
License: MIT
Download-URL: https://github.com/randydu/qbackup/archive/v0.0.1.tar.gz
Keywords: backup,copy
Platform: UNKNOWN
Classifier: Development Status :: 2 - Pre-Alpha
Classifier: Intended Audience :: Developers
Classifier: Operating System :: OS Independent
Classifier: Topic :: Software Development :: Libraries
Classifier: Topic :: Software Development :: Libraries :: Python Modules
Classifier: License :: OSI Approved :: MIT License
Classifier: Programming Language :: Python :: 3
